[{"applicantName":"贵阳南明老干妈风味食品有限责任公司","correspondent":"中原信达知识产权代理有限责任公司","flowLists":[{"name":"变更商标代理人完成","showLastTime":"2016-09-08"},{"name":"补发变更/转让/续展证明申请完成","showLastTime":"2016-07-07"},{"name":"变更商标代理人中","showLastTime":"2016-03-29"},{"name":"补发变更/转让/续展证明申请中","showLastTime":"2016-03-29"},{"name":"商标续展完成","showLastTime":"2015-10-15"},{"name":"商标续展中","showLastTime":"2015-07-20"},{"name":"注册申请部分驳回","showLastTime":"2013-06-03"},{"name":"商标已注册","showLastTime":"2005-11-10"},{"name":"注册申请初步审定","showLastTime":"2005-05-23"},{"name":"注册申请部分驳回","showLastTime":"2005-05-19"},{"name":"打印驳回或部分驳回通知书","showLastTime":"2005-03-24"},{"name":"商标注册申请中","showLastTime":"2003-06-25"}],"goodsLists":[{"code":"4224","name":"艺术品鉴定"},{"code":"4227","name":"无形资产评估"}],"imgAddr":"061f8a2c/3663c830/f7201abe/760730cf/logo_middle.jpg","internationalClasses":42,"localImageAddr":"quandashi/2018/6/15/b803a40d16158e7f86bb1ba24bb4137b.jpg","mark":"老干妈","possessionTermStart":1445356800000,"publishedOppositionDate":1121875200000,"registrationDate":1129824000000,"serialNumber":"3607418","showPossessionTermStart":"2015-10-21","showPublishedOppositionDate":"2005-07-21","showRegistrationDate":"2005-10-21"},{"applicantName":"贵阳南明老干妈风味食品有限责任公司","correspondent":"中原信达知识产权代理有限责任公司","flowLists":[{"name":"变更商标代理人完成","showLastTime":"2016-09-08"},{"name":"变更商标代理人中","showLastTime":"2016-03-29"},{"name":"商标已注册","showLastTime":"2010-04-12"},{"name":"注册申请初步审定","showLastTime":"2009-10-09"},{"name":"注册申请部分驳回","showLastTime":"2009-09-05"},{"name":"注册申请部分驳回","showLastTime":"2009-08-26"},{"name":"打印驳回或部分驳回通知书","showLastTime":"2009-07-01"},{"name":"商标注册申请中","showLastTime":"2008-04-21"}],"goodsLists":[{"code":"2904","name":"以果蔬为主的零食小吃"},{"code":"2905","name":"腐乳"},{"code":"2905","name":"腌制蔬菜"},{"code":"2906","name":"蛋"},{"code":"2911","name":"熟制豆"}],"imgAddr":"d82e00ba/4a9fb5b8/96fa196b/b08a8601/logo_middle.jpg","internationalClasses":29,"localImageAddr":"quandashi/2018/6/15/0dd2e80ca0d48d2a4b7821f684318389.jpg","mark":"老干妈","possessionTermStart":1269100800000,"publishedOppositionDate":1261238400000,"registrationDate":1269100800000,"serialNumber":"6672373","showPossessionTermStart":"2010-03-21","showPublishedOppositionDate":"2009-12-20","showRegistrationDate":"2010-03-21"},{"applicantName":"贵阳南明老干妈风味食品有限责任公司","correspondent":"中原信达知识产权代理有限责任公司","flowLists":[{"name":"等待受理通知书发文","showLastTime":"2016-10-11"},{"name":"申请收文","showLastTime":"2016-05-17"}],"goodsLists":[{"code":"1204","name":"自行车打气筒"},{"code":"1208","name":"补内胎用全套工具"}],"imgAddr":"86337e68/e66076f0/5602e00a/5b755826/logo_middle.jpg","internationalClasses":12,"localImageAddr":"quandashi/2018/6/15/f6757f0eaf9dcb17891e7735ae5b2abf.jpg","mark":"老干妈","possessionTermStart":1499356800000,"publishedOppositionDate":1491408000000,"registrationDate":1499270400000,"serialNumber":"19977195","showPossessionTermStart":"2017-07-07","showPublishedOppositionDate":"2017-04-06","showRegistrationDate":"2017-07-06"},{"applicantName":"深圳恒利投资有限公司","correspondent":"北京晟通阳光知识产权代理有限公司","flowLists":[{"name":"商标异议申请中","showLastTime":"2016-02-22"},{"name":"商标注册申请注册公告排版完成","showLastTime":"2016-02-21"},{"name":"商标注册申请受理通知书发文","showLastTime":"2015-03-28"},{"name":"商标注册申请中","showLastTime":"2014-12-17"}],"goodsLists":[{"code":"3502","name":"公共关系"},{"code":"3502","name":"特许经营的商业管理"},{"code":"3502","name":"通过网站提供商业信息"},{"code":"3502","name":"工商管理辅助"},{"code":"3502","name":"商业研究"},{"code":"3502","name":"商业管理辅助"},{"code":"3502","name":"商业信息"},{"code":"3502","name":"饭店商业管理"},{"code":"3503","name":"替他人推销"},{"code":"3503","name":"市场营销"}],"imgAddr":"20f3875a/fa488def/5148bcbd/69c178b3/logo_middle.jpg","internationalClasses":35,"localImageAddr":"quandashi/2018/6/15/f85080fd9255318d54838d77f3a31feb.jpg","mark":"老干妈","publishedOppositionDate":1447948800000,"serialNumber":"15957532","showPossessionTermStart":"暂无","showPublishedOppositionDate":"2015-11-20","showRegistrationDate":"暂无"},{"applicantName":"江龙发","correspondent":"北京金信立方知识产权代理有限公司","flowLists":[{"name":"商标无效"},{"name":"无效宣告完成","showLastTime":"2011-11-30"},{"name":"无效宣告收到争议申请或补充材料,待审","showLastTime":"2010-05-21"},{"name":"无效宣告中","showLastTime":"2010-05-21"},{"name":"商标已注册","showLastTime":"2005-06-21"},{"name":"注册申请初步审定","showLastTime":"2004-12-27"},{"name":"商标注册申请中","showLastTime":"2003-09-27"}],"goodsLists":[],"imgAddr":"fb21860f/a49ebb51/bc9926d5/99287970/logo_middle.jpg","internationalClasses":11,"localImageAddr":"quandashi/2018/6/15/3003ec336d748b3682c8928dad43b952.jpg","mark":"老干妈","possessionTermStart":1117209600000,"publishedOppositionDate":1109520000000,"registrationDate":1117209600000,"serialNumber":"3734958","showPossessionTermStart":"2005-05-28","showPublishedOppositionDate":"2005-02-28","showRegistrationDate":"2005-05-28"},{"applicantName":"贵阳南明老干妈风味食品有限责任公司","correspondent":"中原信达知识产权代理有限责任公司","flowLists":[{"name":"等待受理通知书发文","showLastTime":"2017-10-27"},{"name":"申请收文","showLastTime":"2017-09-25"},{"name":"变更商标代理人完成","showLastTime":"2016-09-08"},{"name":"变更商标代理人中","showLastTime":"2016-03-29"},{"name":"商标已注册","showLastTime":"2010-10-19"},{"name":"注册申请初步审定","showLastTime":"2010-05-19"},{"name":"注册申请部分驳回","showLastTime":"2010-05-14"},{"name":"注册申请部分驳回","showLastTime":"2010-05-04"},{"name":"打印驳回或部分驳回通知书","showLastTime":"2010-03-09"},{"name":"商标注册申请中","showLastTime":"2008-04-21"}],"goodsLists":[{"code":"3002","name":"茶叶代用品"},{"code":"3004","name":"糖果"},{"code":"3005","name":"非医用营养粉"},{"code":"3006","name":"糕点"},{"code":"3006","name":"以谷物为主的零食小吃"},{"code":"3007","name":"年糕"},{"code":"3008","name":"谷类制品"},{"code":"3009","name":"面粉制品"},{"code":"3010","name":"以谷物为主的零食小吃"},{"code":"3012","name":"含淀粉食品"},{"code":"3016","name":"辣椒油"},{"code":"3016","name":"调味品"},{"code":"3018","name":"食用香料(不包括含醚香料和香精油)"}],"imgAddr":"389d014c/1bb27a7b/751b497f/cc65b4e7/logo_middle.jpg","internationalClasses":30,"localImageAddr":"quandashi/2018/6/15/17a436d5d424086f3ed3d13078f30860.jpg","mark":"老干妈","possessionTermStart":1285603200000,"publishedOppositionDate":1277568000000,"registrationDate":1285603200000,"serialNumber":"6672369","showPossessionTermStart":"2010-09-28","showPublishedOppositionDate":"2010-06-27","showRegistrationDate":"2010-09-28"},{"applicantName":"贵阳南明老干妈风味食品有限责任公司","correspondent":"中原信达知识产权代理有限责任公司","flowLists":[{"name":"等待受理通知书发文","showLastTime":"2016-10-11"},{"name":"申请收文","showLastTime":"2016-05-17"}],"goodsLists":[{"code":"2801","name":"游戏器具"},{"code":"2806","name":"射箭用器具"},{"code":"2807","name":"狩猎用哨子"},{"code":"2808","name":"游泳池（娱乐用品）"},{"code":"2808","name":"塑料跑道"},{"code":"2809","name":"护肘（体育用品）"},{"code":"2809","name":"（冰刀）冰鞋"},{"code":"2812","name":"抽奖用刮刮卡"},{"code":"2812","name":"拉拉队用指挥棒"},{"code":"2812","name":"伪装掩蔽物（运动用品）"},{"code":"2812","name":"球拍用吸汗带"}],"imgAddr":"d31d9f8e/9c14cab3/d6e6dddd/39e905c9/logo_middle.jpg","internationalClasses":28,"localImageAddr":"quandashi/2018/6/15/519a6de3b528cfe12280d11bb290055e.jpg","mark":"老干妈","possessionTermStart":1499356800000,"publishedOppositionDate":1491408000000,"registrationDate":1499270400000,"serialNumber":"19977215","showPossessionTermStart":"2017-07-07","showPublishedOppositionDate":"2017-04-06","showRegistrationDate":"2017-07-06"},{"applicantName":"贵阳南明老干妈风味食品有限责任公司","correspondent":"中原信达知识产权代理有限责任公司","flowLists":[{"name":"变更商标代理人中","showLastTime":"2016-03-29"},{"name":"商标已注册","showLastTime":"2011-06-14"},{"name":"注册申请初步审定","showLastTime":"2011-01-14"},{"name":"商标注册申请中","showLastTime":"2007-08-15"}],"goodsLists":[{"code":"3001","name":"咖啡"},{"code":"3002","name":"茶"},{"code":"3008","name":"谷类制品"},{"code":"3008","name":"米"},{"code":"3014","name":"食盐"},{"code":"3016","name":"调味酱"},{"code":"3016","name":"豆豉"},{"code":"3016","name":"豆酱(调味品)"},{"code":"3016","name":"调味品"},{"code":"3016","name":"佐料(调味品)"}],"imgAddr":"ce25bbea/595282c3/bfa20e7e/f5d164dd/logo_middle.jpg","internationalClasses":30,"localImageAddr":"quandashi/2018/6/15/11ca6a80214d3058c59d3667c7e57365.jpg","mark":"老干妈","possessionTermStart":1305907200000,"publishedOppositionDate":1298131200000,"registrationDate":1305907200000,"serialNumber":"6222661","showPossessionTermStart":"2011-05-21","showPublishedOppositionDate":"2011-02-20","showRegistrationDate":"2011-05-21"},{"applicantName":"贵阳南明老干妈风味食品有限责任公司","correspondent":"中原信达知识产权代理有限责任公司","flowLists":[{"name":"变更商标代理人完成","showLastTime":"2016-09-08"},{"name":"商标续展完成","showLastTime":"2016-05-27"},{"name":"变更商标代理人中","showLastTime":"2016-03-29"},{"name":"商标续展中","showLastTime":"2015-12-01"},{"name":"注册申请部分驳回","showLastTime":"2013-06-03"},{"name":"商标已注册","showLastTime":"2006-02-09"},{"name":"注册申请初步审定","showLastTime":"2005-08-22"},{"name":"注册申请部分驳回","showLastTime":"2005-08-17"},{"name":"打印驳回或部分驳回通知书","showLastTime":"2005-06-22"},{"name":"商标注册申请中","showLastTime":"2003-06-25"}],"goodsLists":[{"code":"2904","name":"果酱"},{"code":"2905","name":"腌制蔬菜"},{"code":"2906","name":"蛋"}],"imgAddr":"ee8fb5c0/3fb688dc/8e5f3812/f1e10a9a/logo_middle.jpg","internationalClasses":29,"localImageAddr":"quandashi/2018/6/15/e363f7f33a306df11ed225824111fda3.jpg","mark":"老干妈","possessionTermStart":1453305600000,"publishedOppositionDate":1129824000000,"registrationDate":1137772800000,"serialNumber":"3607402","showPossessionTermStart":"2016-01-21","showPublishedOppositionDate":"2005-10-21","showRegistrationDate":"2006-01-21"},{"applicantName":"汕头市初雨化妆品有限公司","correspondent":"汕头市腾飞信息产业有限公司","flowLists":[{"name":"商标异议申请完成","showLastTime":"2016-07-06"},{"name":"商标注册申请注册公告排版完成","showLastTime":"2015-02-15"},{"name":"商标异议申请中","showLastTime":"2015-02-13"},{"name":"商标注册申请中","showLastTime":"2013-11-28"}],"goodsLists":[{"code":"3509","name":"兽药零售或批发服务"},{"code":"3509","name":"兽医用制剂零售或批发服务"},{"code":"3509","name":"卫生制剂零售或批发服务"},{"code":"3509","name":"医疗用品零售或批发服务"},{"code":"3509","name":"药用、兽医用、卫生用制剂和医疗用品的零售或批发服务"},{"code":"3509","name":"药用制剂零售或批发服务"},{"code":"3509","name":"药品零售或批发服务"}],"imgAddr":"252cd4e6/24bc838c/827df9ae/eab4f6ed/logo_middle.jpg","internationalClasses":35,"localImageAddr":"quandashi/2018/6/15/0c9d1c46efb7e2de84bdb80a69b2f6b6.jpg","mark":"老干妈","possessionTermStart":1423843200000,"publishedOppositionDate":1415808000000,"registrationDate":1471104000000,"serialNumber":"13631172","showPossessionTermStart":"2015-02-14","showPublishedOppositionDate":"2014-11-13","showRegistrationDate":"2016-08-14"},{"applicantName":"贵阳南明老干妈风味食品有限责任公司","correspondent":"中原信达知识产权代理有限责任公司","flowLists":[{"name":"变更商标代理人完成","showLastTime":"2016-09-08"},{"name":"补发变更/转让/续展证明申请完成","showLastTime":"2016-07-07"},{"name":"变更商标代理人中","showLastTime":"2016-03-29"},{"name":"补发变更/转让/续展证明申请中","showLastTime":"2016-03-29"},{"name":"商标续展完成","showLastTime":"2015-10-15"},{"name":"商标续展中","showLastTime":"2015-07-20"},{"name":"注册申请部分驳回","showLastTime":"2013-06-03"},{"name":"商标已注册","showLastTime":"2005-11-10"},{"name":"注册申请初步审定","showLastTime":"2005-05-23"},{"name":"注册申请部分驳回","showLastTime":"2005-05-19"},{"name":"打印驳回或部分驳回通知书","showLastTime":"2005-03-24"},{"name":"商标注册申请中","showLastTime":"2003-06-25"}],"goodsLists":[{"code":"4224","name":"艺术品鉴定"},{"code":"4227","name":"无形资产评估"}],"imgAddr":"061f8a2c/3663c830/f7201abe/760730cf/logo_middle.jpg","internationalClasses":42,"localImageAddr":"quandashi/2018/6/15/b803a40d16158e7f86bb1ba24bb4137b.jpg","mark":"老干妈","possessionTermStart":1445356800000,"publishedOppositionDate":1121875200000,"registrationDate":1129824000000,"serialNumber":"3607418","showPossessionTermStart":"2015-10-21","showPublishedOppositionDate":"2005-07-21","showRegistrationDate":"2005-10-21"},{"applicantName":"贵阳南明老干妈风味食品有限责任公司","correspondent":"中原信达知识产权代理有限责任公司","flowLists":[{"name":"变更商标代理人完成","showLastTime":"2016-09-08"},{"name":"变更商标代理人中","showLastTime":"2016-03-29"},{"name":"商标已注册","showLastTime":"2010-04-12"},{"name":"注册申请初步审定","showLastTime":"2009-10-09"},{"name":"注册申请部分驳回","showLastTime":"2009-09-05"},{"name":"注册申请部分驳回","showLastTime":"2009-08-26"},{"name":"打印驳回或部分驳回通知书","showLastTime":"2009-07-01"},{"name":"商标注册申请中","showLastTime":"2008-04-21"}],"goodsLists":[{"code":"2904","name":"以果蔬为主的零食小吃"},{"code":"2905","name":"腐乳"},{"code":"2905","name":"腌制蔬菜"},{"code":"2906","name":"蛋"},{"code":"2911","name":"熟制豆"}],"imgAddr":"d82e00ba/4a9fb5b8/96fa196b/b08a8601/logo_middle.jpg","internationalClasses":29,"localImageAddr":"quandashi/2018/6/15/0dd2e80ca0d48d2a4b7821f684318389.jpg","mark":"老干妈","possessionTermStart":1269100800000,"publishedOppositionDate":1261238400000,"registrationDate":1269100800000,"serialNumber":"6672373","showPossessionTermStart":"2010-03-21","showPublishedOppositionDate":"2009-12-20","showRegistrationDate":"2010-03-21"},{"applicantName":"贵阳南明老干妈风味食品有限责任公司","correspondent":"中原信达知识产权代理有限责任公司","flowLists":[{"name":"等待受理通知书发文","showLastTime":"2016-10-11"},{"name":"申请收文","showLastTime":"2016-05-17"}],"goodsLists":[{"code":"1204","name":"自行车打气筒"},{"code":"1208","name":"补内胎用全套工具"}],"imgAddr":"86337e68/e66076f0/5602e00a/5b755826/logo_middle.jpg","internationalClasses":12,"localImageAddr":"quandashi/2018/6/15/f6757f0eaf9dcb17891e7735ae5b2abf.jpg","mark":"老干妈","possessionTermStart":1499356800000,"publishedOppositionDate":1491408000000,"registrationDate":1499270400000,"serialNumber":"19977195","showPossessionTermStart":"2017-07-07","showPublishedOppositionDate":"2017-04-06","showRegistrationDate":"2017-07-06"},{"applicantName":"深圳恒利投资有限公司","correspondent":"北京晟通阳光知识产权代理有限公司","flowLists":[{"name":"商标异议申请中","showLastTime":"2016-02-22"},{"name":"商标注册申请注册公告排版完成","showLastTime":"2016-02-21"},{"name":"商标注册申请受理通知书发文","showLastTime":"2015-03-28"},{"name":"商标注册申请中","showLastTime":"2014-12-17"}],"goodsLists":[{"code":"3502","name":"公共关系"},{"code":"3502","name":"特许经营的商业管理"},{"code":"3502","name":"通过网站提供商业信息"},{"code":"3502","name":"工商管理辅助"},{"code":"3502","name":"商业研究"},{"code":"3502","name":"商业管理辅助"},{"code":"3502","name":"商业信息"},{"code":"3502","name":"饭店商业管理"},{"code":"3503","name":"替他人推销"},{"code":"3503","name":"市场营销"}],"imgAddr":"20f3875a/fa488def/5148bcbd/69c178b3/logo_middle.jpg","internationalClasses":35,"localImageAddr":"quandashi/2018/6/15/f85080fd9255318d54838d77f3a31feb.jpg","mark":"老干妈","publishedOppositionDate":1447948800000,"serialNumber":"15957532","showPossessionTermStart":"暂无","showPublishedOppositionDate":"2015-11-20","showRegistrationDate":"暂无"},{"applicantName":"江龙发","correspondent":"北京金信立方知识产权代理有限公司","flowLists":[{"name":"商标无效"},{"name":"无效宣告完成","showLastTime":"2011-11-30"},{"name":"无效宣告收到争议申请或补充材料,待审","showLastTime":"2010-05-21"},{"name":"无效宣告中","showLastTime":"2010-05-21"},{"name":"商标已注册","showLastTime":"2005-06-21"},{"name":"注册申请初步审定","showLastTime":"2004-12-27"},{"name":"商标注册申请中","showLastTime":"2003-09-27"}],"goodsLists":[],"imgAddr":"fb21860f/a49ebb51/bc9926d5/99287970/logo_middle.jpg","internationalClasses":11,"localImageAddr":"quandashi/2018/6/15/3003ec336d748b3682c8928dad43b952.jpg","mark":"老干妈","possessionTermStart":1117209600000,"publishedOppositionDate":1109520000000,"registrationDate":1117209600000,"serialNumber":"3734958","showPossessionTermStart":"2005-05-28","showPublishedOppositionDate":"2005-02-28","showRegistrationDate":"2005-05-28"},{"applicantName":"贵阳南明老干妈风味食品有限责任公司","correspondent":"中原信达知识产权代理有限责任公司","flowLists":[{"name":"等待受理通知书发文","showLastTime":"2017-10-27"},{"name":"申请收文","showLastTime":"2017-09-25"},{"name":"变更商标代理人完成","showLastTime":"2016-09-08"},{"name":"变更商标代理人中","showLastTime":"2016-03-29"},{"name":"商标已注册","showLastTime":"2010-10-19"},{"name":"注册申请初步审定","showLastTime":"2010-05-19"},{"name":"注册申请部分驳回","showLastTime":"2010-05-14"},{"name":"注册申请部分驳回","showLastTime":"2010-05-04"},{"name":"打印驳回或部分驳回通知书","showLastTime":"2010-03-09"},{"name":"商标注册申请中","showLastTime":"2008-04-21"}],"goodsLists":[{"code":"3002","name":"茶叶代用品"},{"code":"3004","name":"糖果"},{"code":"3005","name":"非医用营养粉"},{"code":"3006","name":"糕点"},{"code":"3006","name":"以谷物为主的零食小吃"},{"code":"3007","name":"年糕"},{"code":"3008","name":"谷类制品"},{"code":"3009","name":"面粉制品"},{"code":"3010","name":"以谷物为主的零食小吃"},{"code":"3012","name":"含淀粉食品"},{"code":"3016","name":"辣椒油"},{"code":"3016","name":"调味品"},{"code":"3018","name":"食用香料(不包括含醚香料和香精油)"}],"imgAddr":"389d014c/1bb27a7b/751b497f/cc65b4e7/logo_middle.jpg","internationalClasses":30,"localImageAddr":"quandashi/2018/6/15/17a436d5d424086f3ed3d13078f30860.jpg","mark":"老干妈","possessionTermStart":1285603200000,"publishedOppositionDate":1277568000000,"registrationDate":1285603200000,"serialNumber":"6672369","showPossessionTermStart":"2010-09-28","showPublishedOppositionDate":"2010-06-27","showRegistrationDate":"2010-09-28"},{"applicantName":"贵阳南明老干妈风味食品有限责任公司","correspondent":"中原信达知识产权代理有限责任公司","flowLists":[{"name":"等待受理通知书发文","showLastTime":"2016-10-11"},{"name":"申请收文","showLastTime":"2016-05-17"}],"goodsLists":[{"code":"2801","name":"游戏器具"},{"code":"2806","name":"射箭用器具"},{"code":"2807","name":"狩猎用哨子"},{"code":"2808","name":"游泳池（娱乐用品）"},{"code":"2808","name":"塑料跑道"},{"code":"2809","name":"护肘（体育用品）"},{"code":"2809","name":"（冰刀）冰鞋"},{"code":"2812","name":"抽奖用刮刮卡"},{"code":"2812","name":"拉拉队用指挥棒"},{"code":"2812","name":"伪装掩蔽物（运动用品）"},{"code":"2812","name":"球拍用吸汗带"}],"imgAddr":"d31d9f8e/9c14cab3/d6e6dddd/39e905c9/logo_middle.jpg","internationalClasses":28,"localImageAddr":"quandashi/2018/6/15/519a6de3b528cfe12280d11bb290055e.jpg","mark":"老干妈","possessionTermStart":1499356800000,"publishedOppositionDate":1491408000000,"registrationDate":1499270400000,"serialNumber":"19977215","showPossessionTermStart":"2017-07-07","showPublishedOppositionDate":"2017-04-06","showRegistrationDate":"2017-07-06"},{"applicantName":"贵阳南明老干妈风味食品有限责任公司","correspondent":"中原信达知识产权代理有限责任公司","flowLists":[{"name":"变更商标代理人中","showLastTime":"2016-03-29"},{"name":"商标已注册","showLastTime":"2011-06-14"},{"name":"注册申请初步审定","showLastTime":"2011-01-14"},{"name":"商标注册申请中","showLastTime":"2007-08-15"}],"goodsLists":[{"code":"3001","name":"咖啡"},{"code":"3002","name":"茶"},{"code":"3008","name":"谷类制品"},{"code":"3008","name":"米"},{"code":"3014","name":"食盐"},{"code":"3016","name":"调味酱"},{"code":"3016","name":"豆豉"},{"code":"3016","name":"豆酱(调味品)"},{"code":"3016","name":"调味品"},{"code":"3016","name":"佐料(调味品)"}],"imgAddr":"ce25bbea/595282c3/bfa20e7e/f5d164dd/logo_middle.jpg","internationalClasses":30,"localImageAddr":"quandashi/2018/6/15/11ca6a80214d3058c59d3667c7e57365.jpg","mark":"老干妈","possessionTermStart":1305907200000,"publishedOppositionDate":1298131200000,"registrationDate":1305907200000,"serialNumber":"6222661","showPossessionTermStart":"2011-05-21","showPublishedOppositionDate":"2011-02-20","showRegistrationDate":"2011-05-21"},{"applicantName":"贵阳南明老干妈风味食品有限责任公司","correspondent":"中原信达知识产权代理有限责任公司","flowLists":[{"name":"变更商标代理人完成","showLastTime":"2016-09-08"},{"name":"商标续展完成","showLastTime":"2016-05-27"},{"name":"变更商标代理人中","showLastTime":"2016-03-29"},{"name":"商标续展中","showLastTime":"2015-12-01"},{"name":"注册申请部分驳回","showLastTime":"2013-06-03"},{"name":"商标已注册","showLastTime":"2006-02-09"},{"name":"注册申请初步审定","showLastTime":"2005-08-22"},{"name":"注册申请部分驳回","showLastTime":"2005-08-17"},{"name":"打印驳回或部分驳回通知书","showLastTime":"2005-06-22"},{"name":"商标注册申请中","showLastTime":"2003-06-25"}],"goodsLists":[{"code":"2904","name":"果酱"},{"code":"2905","name":"腌制蔬菜"},{"code":"2906","name":"蛋"}],"imgAddr":"ee8fb5c0/3fb688dc/8e5f3812/f1e10a9a/logo_middle.jpg","internationalClasses":29,"localImageAddr":"quandashi/2018/6/15/e363f7f33a306df11ed225824111fda3.jpg","mark":"老干妈","possessionTermStart":1453305600000,"publishedOppositionDate":1129824000000,"registrationDate":1137772800000,"serialNumber":"3607402","showPossessionTermStart":"2016-01-21","showPublishedOppositionDate":"2005-10-21","showRegistrationDate":"2006-01-21"},{"applicantName":"汕头市初雨化妆品有限公司","correspondent":"汕头市腾飞信息产业有限公司","flowLists":[{"name":"商标异议申请完成","showLastTime":"2016-07-06"},{"name":"商标注册申请注册公告排版完成","showLastTime":"2015-02-15"},{"name":"商标异议申请中","showLastTime":"2015-02-13"},{"name":"商标注册申请中","showLastTime":"2013-11-28"}],"goodsLists":[{"code":"3509","name":"兽药零售或批发服务"},{"code":"3509","name":"兽医用制剂零售或批发服务"},{"code":"3509","name":"卫生制剂零售或批发服务"},{"code":"3509","name":"医疗用品零售或批发服务"},{"code":"3509","name":"药用、兽医用、卫生用制剂和医疗用品的零售或批发服务"},{"code":"3509","name":"药用制剂零售或批发服务"},{"code":"3509","name":"药品零售或批发服务"}],"imgAddr":"252cd4e6/24bc838c/827df9ae/eab4f6ed/logo_middle.jpg","internationalClasses":35,"localImageAddr":"quandashi/2018/6/15/0c9d1c46efb7e2de84bdb80a69b2f6b6.jpg","mark":"老干妈","possessionTermStart":1423843200000,"publishedOppositionDate":1415808000000,"registrationDate":1471104000000,"serialNumber":"13631172","showPossessionTermStart":"2015-02-14","showPublishedOppositionDate":"2014-11-13","showRegistrationDate":"2016-08-14"},{"applicantName":"朱鸿儒","correspondent":"重庆猪八戒知识产权服务有限公司第四分公司","flowLists":[{"name":"等待受理通知书发文","showLastTime":"2016-11-04"},{"name":"商标注册申请受理通知书发文","showLastTime":"2016-11-04"},{"name":"申请收文","showLastTime":"2016-06-13"},{"name":"商标注册申请中","showLastTime":"2016-06-13"}],"goodsLists":[{"code":"3006","name":"油茶粉"},{"code":"3006","name":"糕点"},{"code":"3006","name":"以谷物为主的零食小吃"},{"code":"3007","name":"粥"},{"code":"3008","name":"谷类制品"},{"code":"3008","name":"谷粉"},{"code":"3008","name":"人食用的去壳谷物"},{"code":"3010","name":"以谷物为主的零食小吃"},{"code":"3011","name":"豆粉"},{"code":"3016","name":"调味料"},{"code":"3016","name":"除香精油外的食物用调味品"},{"code":"3018","name":"除香精油外的食物用调味品"}],"imgAddr":"6883a2c2/1cc171ae/3165f3b1/2062fecb/logo_middle.jpg","internationalClasses":30,"localImageAddr":"quandashi/2018/6/15/c59a6ce2d4170d7e22f8624a66ea35db.jpg","mark":"老谷妈","publishedOppositionDate":1493222400000,"registrationDate":1501084800000,"serialNumber":"20279116","showPossessionTermStart":"暂无","showPublishedOppositionDate":"2017-04-27","showRegistrationDate":"2017-07-27"},{"applicantName":"北京美旺商贸有限公司","correspondent":"北京坤佑知识产权代理有限公司","flowLists":[{"name":"商标注册申请注册公告排版完成","showLastTime":"2015-08-10"},{"name":"商标注册申请受理通知书发文","showLastTime":"2014-10-13"},{"name":"商标注册申请中","showLastTime":"2014-06-11"}],"goodsLists":[{"code":"3001","name":"巧克力酱"},{"code":"3002","name":"茶"},{"code":"3006","name":"糕点"},{"code":"3006","name":"谷粉制食品"},{"code":"3006","name":"以谷物为主的零食小吃"},{"code":"3007","name":"谷粉制食品"},{"code":"3008","name":"谷类制品"},{"code":"3009","name":"谷粉制食品"},{"code":"3010","name":"以谷物为主的零食小吃"},{"code":"3012","name":"谷粉制食品"},{"code":"3016","name":"调味品"},{"code":"3016","name":"酱菜（调味品）"},{"code":"3016","name":"姜（调味品）"},{"code":"3016","name":"调味酱"}],"imgAddr":"74d475f4/c96438c8/375f7219/8841a5d3/logo_middle.jpg","internationalClasses":30,"localImageAddr":"quandashi/2018/6/15/51bb1aedd151fcb6cb1f35931262cafa.jpg","mark":"老姜妈","publishedOppositionDate":1430841600000,"serialNumber":"14840952","showPossessionTermStart":"暂无","showPublishedOppositionDate":"2015-05-06","showRegistrationDate":"暂无"},{"applicantName":"北京美旺商贸有限公司","correspondent":"北京坤佑知识产权代理有限公司","flowLists":[{"name":"商标注册申请注册公告排版完成","showLastTime":"2015-08-10"},{"name":"商标注册申请受理通知书发文","showLastTime":"2014-10-13"},{"name":"商标注册申请中","showLastTime":"2014-06-11"}],"goodsLists":[{"code":"0301","name":"非医用洗浴制剂"},{"code":"0301","name":"浴液"},{"code":"0301","name":"洁肤乳液"},{"code":"0301","name":"洗面奶"},{"code":"0302","name":"清洁制剂"},{"code":"0305","name":"芳香精油"},{"code":"0306","name":"化妆品"},{"code":"0306","name":"护肤用化妆剂"},{"code":"0307","name":"非医用漱口剂"},{"code":"0308","name":"干花瓣与香料混合物（香料）"}],"imgAddr":"74d475f4/c96438c8/375f7219/8841a5d3/logo_middle.jpg","internationalClasses":3,"localImageAddr":"quandashi/2018/6/15/51bb1aedd151fcb6cb1f35931262cafa.jpg","mark":"老姜妈","possessionTermStart":1438876800000,"publishedOppositionDate":1430841600000,"registrationDate":1492099200000,"serialNumber":"14840952","showPossessionTermStart":"2015-08-07","showPublishedOppositionDate":"2015-05-06","showRegistrationDate":"2017-04-14"},{"applicantName":"上海阳初生物科技有限公司","correspondent":"上海涵哲知识产权代理有限公司","flowLists":[{"name":"等待受理通知书发文","showLastTime":"2016-12-08"},{"name":"申请收文","showLastTime":"2016-10-26"}],"goodsLists":[{"code":"3002","name":"茶"},{"code":"3003","name":"糖"},{"code":"3004","name":"糖"},{"code":"3005","name":"冰糖燕窝"},{"code":"3006","name":"以谷物为主的零食小吃"},{"code":"3008","name":"谷类制品"},{"code":"3009","name":"面条"},{"code":"3010","name":"以谷物为主的零食小吃"},{"code":"3014","name":"食盐"},{"code":"3016","name":"调味品"},{"code":"3016","name":"调味酱"},{"code":"3018","name":"食品用香料（含醚香料和香精油除外）"}],"imgAddr":"5a50c1af/fb5e2776/d4ff63cf/9a86f5da/logo_middle.jpg","internationalClasses":30,"localImageAddr":"quandashi/2018/6/15/695e9dc858594e7b19a2819517bb18c6.jpg","mark":"老椿妈","publishedOppositionDate":1505232000000,"registrationDate":1513094400000,"serialNumber":"21689633","showPossessionTermStart":"暂无","showPublishedOppositionDate":"2017-09-13","showRegistrationDate":"2017-12-13"},{"applicantName":"乔中峰","correspondent":"郑州宏盛知识产权代理有限公司","flowLists":[{"name":"商标注册申请完成","showLastTime":"2016-04-28"},{"name":"商标注册申请注册公告排版完成","showLastTime":"2015-11-29"},{"name":"商标注册申请受理通知书发文","showLastTime":"2014-12-16"},{"name":"商标注册申请中","showLastTime":"2014-10-11"}],"goodsLists":[{"code":"3001","name":"加奶咖啡饮料"},{"code":"3002","name":"茶饮料"},{"code":"3002","name":"茶"},{"code":"3005","name":"龟苓膏"},{"code":"3006","name":"谷粉制食品"},{"code":"3007","name":"粥"},{"code":"3007","name":"谷粉制食品"},{"code":"3009","name":"谷粉制食品"},{"code":"3012","name":"谷粉制食品"},{"code":"3013","name":"食用冰"},{"code":"3015","name":"酱油"},{"code":"3016","name":"豆豉"},{"code":"3016","name":"豆酱（调味品）"}],"imgAddr":"a86bea85/d5e87f96/5d21333b/22d00825/logo_middle.jpg","internationalClasses":30,"localImageAddr":"quandashi/2018/6/15/cc397d70c2e0e375c7464f7c84fc908c.jpg","mark":"老酱妈","possessionTermStart":1448640000000,"publishedOppositionDate":1440604800000,"registrationDate":1448640000000,"serialNumber":"15485466","showPossessionTermStart":"2015-11-28","showPublishedOppositionDate":"2015-08-27","showRegistrationDate":"2015-11-28"},{"applicantName":"贵州老吴公酒业有限公司","correspondent":"贵州睿朗商标代理咨询有限公司","flowLists":[{"name":"商标已注册","showLastTime":"2011-09-09"},{"name":"注册申请初步审定","showLastTime":"2011-04-18"},{"name":"商标注册申请中","showLastTime":"2010-08-02"}],"goodsLists":[{"code":"3301","name":"果酒(含酒精)"},{"code":"3301","name":"含酒精液体"},{"code":"3301","name":"黄酒"},{"code":"3301","name":"酒(饮料)"},{"code":"3301","name":"烧酒"},{"code":"3301","name":"开胃酒"},{"code":"3301","name":"料酒"},{"code":"3301","name":"米酒"},{"code":"3301","name":"葡萄酒"},{"code":"3301","name":"酒精饮料(啤酒除外)"}],"imgAddr":"6bb4ac54/f97b649f/ce9a397c/dad74b4e/logo_middle.jpg","internationalClasses":33,"localImageAddr":"quandashi/2018/6/15/87fba638792e437961a0b066a4238ffb.jpg","mark":"老熊妈","possessionTermStart":1313856000000,"publishedOppositionDate":1305820800000,"registrationDate":1313856000000,"serialNumber":"8534879","showPossessionTermStart":"2011-08-21","showPublishedOppositionDate":"2011-05-20","showRegistrationDate":"2011-08-21"},{"applicantName":"杨克翠","correspondent":"大连市东北联合商标事务所有限公司","flowLists":[{"name":"商标注册申请等待受理中 "}],"goodsLists":[{"code":"3012","name":"粉丝（条）"},{"code":"3015","name":"酱油"},{"code":"3016","name":"调味品"},{"code":"3017","name":"烹饪用小苏打"},{"code":"3004","name":"糖"},{"code":"3005","name":"蜂蜜"},{"code":"3006","name":"月饼"},{"code":"3007","name":"煎饼"},{"code":"3008","name":"米"},{"code":"3009","name":"面条"},{"code":"3003","name":"糖"}],"imgAddr":"e552ac16/6655bfc5/8677b8c9/313226a4/logo_middle.jpg","internationalClasses":30,"localImageAddr":"quandashi/2018/6/15/853b18c593563f15a81d645dfb6c0902.jpg","mark":"老阿妈","publishedOppositionDate":1524758400000,"serialNumber":"22797463","showPossessionTermStart":"暂无","showPublishedOppositionDate":"2018-04-27","showRegistrationDate":"暂无"},{"applicantName":"贵州聚福轩茶业食品有限公司","correspondent":"贵州红徽防伪科技有限公司","flowLists":[{"name":"商标注册申请完成","showLastTime":"2015-04-15"},{"name":"商标注册申请注册公告排版完成","showLastTime":"2015-03-02"},{"name":"商标注册申请中","showLastTime":"2013-11-22"}],"goodsLists":[{"code":"3501","name":"电视广告"},{"code":"3501","name":"广告代理"},{"code":"3501","name":"广告设计"},{"code":"3501","name":"广告策划"},{"code":"3501","name":"广告"},{"code":"3502","name":"特许经营的商业管理"},{"code":"3502","name":"饭店商业管理"},{"code":"3503","name":"替他人采购(替其他企业购买商品或服务)"},{"code":"3503","name":"替他人推销"},{"code":"3503","name":"进出口代理"}],"imgAddr":"a40bf81b/4638a763/c6050d6c/a27bb001/logo_middle.jpg","internationalClasses":35,"localImageAddr":"quandashi/2018/6/15/2f5f7b7cbeb285d50028dbd4acc11111.jpg","mark":"老茶妈","possessionTermStart":1424448000000,"publishedOppositionDate":1416412800000,"registrationDate":1424448000000,"serialNumber":"13592793","showPossessionTermStart":"2015-02-21","showPublishedOppositionDate":"2014-11-20","showRegistrationDate":"2015-02-21"},{"applicantName":"李皖清","flowLists":[{"name":"等待驳回复审","showLastTime":"2017-01-13"},{"name":"等待驳回通知发文","showLastTime":"2016-11-19"},{"name":"等待受理通知书发文","showLastTime":"2016-06-16"},{"name":"申请收文","showLastTime":"2016-01-25"}],"goodsLists":[{"code":"2901","name":"食用燕窝"},{"code":"2902","name":"鱼制食品"},{"code":"2904","name":"以果蔬为主的零食小吃"},{"code":"2904","name":"芝麻酱"},{"code":"2905","name":"酱菜"},{"code":"2907","name":"奶茶（以奶为主）"},{"code":"2908","name":"芝麻油"},{"code":"2910","name":"果冻"},{"code":"2911","name":"以果蔬为主的零食小吃"},{"code":"2912","name":"干食用菌"},{"code":"2913","name":"豆腐制品"}],"imgAddr":"4cd16e44/d9150051/591ffb77/6935aabf/logo_middle.jpg","internationalClasses":29,"localImageAddr":"quandashi/2018/6/15/5d7983b76b8cfd1701a9746216f380e7.jpg","mark":"老酸妈","possessionTermStart":1495296000000,"publishedOppositionDate":1487520000000,"registrationDate":1495296000000,"serialNumber":"18975355","showPossessionTermStart":"2017-05-21","showPublishedOppositionDate":"2017-02-20","showRegistrationDate":"2017-05-21"},{"applicantName":"朱小东","correspondent":"沈阳鸿盛知识产权代理有限公司","flowLists":[{"name":"等待受理通知书发文","showLastTime":"2016-11-30"},{"name":"申请收文","showLastTime":"2016-09-19"}],"goodsLists":[{"code":"0501","name":"医用膏药"},{"code":"0501","name":"补药"},{"code":"0501","name":"人参"},{"code":"0501","name":"医用药物"},{"code":"0501","name":"贴剂"},{"code":"0501","name":"芥子膏药"},{"code":"0501","name":"医用香膏"},{"code":"0502","name":"医用营养品"},{"code":"0506","name":"药枕"},{"code":"0507","name":"出牙剂"}],"imgAddr":"39e68345/cac8a579/77c3b5ee/1b801cea/logo_middle.jpg","internationalClasses":5,"localImageAddr":"quandashi/2018/6/15/85f218d98eaaccac03e8a6bfad775b7a.jpg","mark":"老亲妈","publishedOppositionDate":1502553600000,"registrationDate":1510502400000,"serialNumber":"21341674","showPossessionTermStart":"暂无","showPublishedOppositionDate":"2017-08-13","showRegistrationDate":"2017-11-13"},{"applicantName":"符德广","correspondent":"山东欧赛网络科技有限公司","flowLists":[],"goodsLists":[{"code":"3012","name":"食用淀粉"},{"code":"3008","name":"米粉（粉状）"},{"code":"3009","name":"方便粉丝"},{"code":"3006","name":"糕点"},{"code":"3006","name":"甜食"},{"code":"3004","name":"甜食"},{"code":"3009","name":"米粉（条状）"},{"code":"3008","name":"谷粉"},{"code":"3002","name":"茶饮料"},{"code":"3018","name":"食品用香料（含醚香料和香精油除外）"},{"code":"3016","name":"调味品"}],"imgAddr":"6b5a560a/e597eb29/1f1f1271/aae3661a/logo_middle.jpg","internationalClasses":30,"localImageAddr":"quandashi/2018/6/15/e906d7d523b3a05a3cc1eb644b067345.jpg","mark":"老谭妈","publishedOppositionDate":1518451200000,"registrationDate":1526140800000,"serialNumber":"22904023","showPossessionTermStart":"暂无","showPublishedOppositionDate":"2018-02-13","showRegistrationDate":"2018-05-13"},{"applicantName":"刘志国","correspondent":"北京聚集科技有限公司","flowLists":[{"name":"等待驳回通知发文","showLastTime":"2017-03-27"},{"name":"等待受理通知书发文","showLastTime":"2016-10-19"},{"name":"申请收文","showLastTime":"2016-05-17"}],"goodsLists":[{"code":"3501","name":"广告宣传"},{"code":"3501","name":"商业橱窗布置"},{"code":"3501","name":"计算机网络上的在线广告"},{"code":"3502","name":"特许经营的商业管理"},{"code":"3502","name":"饭店商业管理"},{"code":"3502","name":"通过网站提供商业信息"},{"code":"3503","name":"市场营销"},{"code":"3503","name":"为商品和服务的买卖双方提供在线市场"},{"code":"3503","name":"替他人推销"},{"code":"3506","name":"开发票"}],"imgAddr":"217fc85e/6ec1fa6e/e0053ca0/1a57e547/logo_middle.jpg","internationalClasses":35,"localImageAddr":"quandashi/2018/6/15/b6d1e04580ef8fcf4b56abecb6d060dc.jpg","mark":"老祥妈","possessionTermStart":1497369600000,"registrationDate":1497369600000,"serialNumber":"19769741","showPossessionTermStart":"2017-06-14","showPublishedOppositionDate":"暂无","showRegistrationDate":"2017-06-14"},{"applicantName":"冷文革","correspondent":"南昌卓尔商标事务所有限公司","flowLists":[{"name":"等待注册证发文","showLastTime":"2017-01-07"},{"name":"商标注册申请完成","showLastTime":"2017-01-07"},{"name":"商标注册申请注册公告排版完成","showLastTime":"2016-10-29"},{"name":"等待受理通知书发文","showLastTime":"2015-12-28"},{"name":"申请收文","showLastTime":"2015-09-18"}],"goodsLists":[{"code":"2904","name":"以果蔬为主的零食小吃"},{"code":"2905","name":"干蔬菜"},{"code":"2905","name":"榨菜"},{"code":"2905","name":"笋干"},{"code":"2905","name":"腐乳"},{"code":"2905","name":"腌制蔬菜"},{"code":"2905","name":"萝卜干"},{"code":"2911","name":"以果蔬为主的零食小吃"},{"code":"2912","name":"干食用菌"},{"code":"2913","name":"腐竹"},{"code":"2913","name":"豆腐"}],"imgAddr":"1a6a00db/cbd4c982/1d3b535a/2a1799c2/logo_middle.jpg","internationalClasses":29,"localImageAddr":"quandashi/2018/6/15/56c1ed2c8c1e6dff0751edc8f2bc2f18.jpg","mark":"老丁妈","possessionTermStart":1477584000000,"publishedOppositionDate":1469548800000,"registrationDate":1477584000000,"serialNumber":"17935356","showPossessionTermStart":"2016-10-28","showPublishedOppositionDate":"2016-07-27","showRegistrationDate":"2016-10-28"},{"applicantName":"白光龙","correspondent":"贵州华信商标代理有限公司","flowLists":[{"name":"商标已注册","showLastTime":"2007-09-03"},{"name":"注册申请初步审定","showLastTime":"2007-03-23"},{"name":"商标注册申请中","showLastTime":"2005-01-19"}],"goodsLists":[{"code":"3016","name":"调味品"},{"code":"3016","name":"调味品(辣)"},{"code":"3016","name":"辣椒粉"},{"code":"3016","name":"番茄酱(调味品)"},{"code":"3016","name":"调味酱"},{"code":"3016","name":"酱菜(调味品)"},{"code":"3016","name":"豆豉"},{"code":"3016","name":"辣椒油"},{"code":"3016","name":"花椒粉"},{"code":"3016","name":"胡椒"}],"imgAddr":"dc7058de/f1317a18/f3668cbd/2c46c0fd/logo_middle.jpg","internationalClasses":30,"localImageAddr":"quandashi/2018/6/15/d216719975bff6f91f806673ea2c1802.jpg","mark":"老白妈","possessionTermStart":1187020800000,"publishedOppositionDate":1179072000000,"registrationDate":1187020800000,"serialNumber":"4470416","showPossessionTermStart":"2007-08-14","showPublishedOppositionDate":"2007-05-14","showRegistrationDate":"2007-08-14"},{"applicantName":"欧阳晃生","flowLists":[{"name":"等待受理通知书发文"}],"goodsLists":[{"code":"3016","name":"肉桂粉（调味品）"},{"code":"3019","name":"家用嫩肉剂"},{"code":"3016","name":"调味酱汁"},{"code":"3016","name":"调味品"},{"code":"3016","name":"调味肉汁"},{"code":"3008","name":"谷类制品"},{"code":"3007","name":"盒饭"},{"code":"3004","name":"糖"},{"code":"3003","name":"糖"},{"code":"3016","name":"调味料"},{"code":"3017","name":"烹饪用碱"}],"imgAddr":"14d5aa30/eed45280/42481323/a266629d/logo_middle.jpg","internationalClasses":30,"localImageAddr":"quandashi/2018/6/15/941640572977b32561eceb524f0f97fb.jpg","mark":"老卤妈","publishedOppositionDate":1525536000000,"serialNumber":"25459504","showPossessionTermStart":"暂无","showPublishedOppositionDate":"2018-05-06","showRegistrationDate":"暂无"},{"applicantName":"王慧婵","correspondent":"中国商标专利事务所有限公司","flowLists":[],"goodsLists":[{"code":"3009","name":"方便面"},{"code":"3008","name":"米"},{"code":"3009","name":"面条"},{"code":"3016","name":"番茄酱（调味品）"},{"code":"3002","name":"茶"},{"code":"","name":"米粉"},{"code":"3012","name":"地瓜粉"},{"code":"3006","name":"饼干"},{"code":"3006","name":"燕麦食品"},{"code":"3006","name":"面包"},{"code":"3009","name":"通心粉"},{"code":"3008","name":"面粉"},{"code":"3012","name":"粉丝（条）"},{"code":"3006","name":"月饼"}],"imgAddr":"0a0e626c/eb3fc73b/b9cee948/510952c4/logo_middle.jpg","internationalClasses":30,"localImageAddr":"quandashi/2018/6/15/944259da69b39e7dc8c8ca9054a0c553.jpg","mark":"老莞妈","publishedOppositionDate":1510502400000,"registrationDate":1518451200000,"serialNumber":"22493486","showPossessionTermStart":"暂无","showPublishedOppositionDate":"2017-11-13","showRegistrationDate":"2018-02-13"},{"applicantName":"童小军","correspondent":"北京标邦知识产权代理有限公司","flowLists":[{"name":"商标无效"},{"name":"商标注册申请等待驳回复审","showLastTime":"2015-01-27"},{"name":"商标注册申请驳回通知发文","showLastTime":"2014-12-02"},{"name":"商标注册申请中","showLastTime":"2013-11-12"}],"goodsLists":[{"code":"2906","name":"蛋"},{"code":"2907","name":"奶油(奶制品)"},{"code":"2907","name":"豆奶(牛奶替代品)"},{"code":"2911","name":"加工过的种子"},{"code":"2912","name":"木耳"},{"code":"2913","name":"烹饪用蛋白"},{"code":"2913","name":"腐竹"},{"code":"2912","name":"干食用菌"},{"code":"2913","name":"豆腐制品"},{"code":"2913","name":"豆腐"}],"imgAddr":"3cfab0d1/f1135e27/0a1865b0/3c4d9d8e/logo_middle.jpg","internationalClasses":29,"localImageAddr":"quandashi/2018/6/15/cfdf0c6fb3763f708e2c8228c2b85820.jpg","mark":"老佛妈","serialNumber":"13525411","showPossessionTermStart":"暂无","showPublishedOppositionDate":"暂无","showRegistrationDate":"暂无"},{"applicantName":"李皖清","flowLists":[{"name":"等待驳回复审","showLastTime":"2017-01-13"},{"name":"等待驳回通知发文","showLastTime":"2016-11-19"},{"name":"等待受理通知书发文","showLastTime":"2016-06-16"},{"name":"申请收文","showLastTime":"2016-01-25"}],"goodsLists":[{"code":"2901","name":"食用燕窝"},{"code":"2902","name":"鱼制食品"},{"code":"2904","name":"以果蔬为主的零食小吃"},{"code":"2904","name":"芝麻酱"},{"code":"2905","name":"酱菜"},{"code":"2907","name":"奶茶（以奶为主）"},{"code":"2908","name":"芝麻油"},{"code":"2910","name":"果冻"},{"code":"2911","name":"以果蔬为主的零食小吃"},{"code":"2912","name":"干食用菌"},{"code":"2913","name":"豆腐制品"}],"imgAddr":"4cd16e44/d9150051/591ffb77/6935aabf/logo_middle.jpg","internationalClasses":29,"localImageAddr":"quandashi/2018/6/15/5d7983b76b8cfd1701a9746216f380e7.jpg","mark":"老酸妈","possessionTermStart":1495296000000,"publishedOppositionDate":1487520000000,"registrationDate":1495296000000,"serialNumber":"18975355","showPossessionTermStart":"2017-05-21","showPublishedOppositionDate":"2017-02-20","showRegistrationDate":"2017-05-21"},{"applicantName":"朱小东","correspondent":"沈阳鸿盛知识产权代理有限公司","flowLists":[{"name":"等待受理通知书发文","showLastTime":"2016-11-30"},{"name":"申请收文","showLastTime":"2016-09-19"}],"goodsLists":[{"code":"0501","name":"医用膏药"},{"code":"0501","name":"补药"},{"code":"0501","name":"人参"},{"code":"0501","name":"医用药物"},{"code":"0501","name":"贴剂"},{"code":"0501","name":"芥子膏药"},{"code":"0501","name":"医用香膏"},{"code":"0502","name":"医用营养品"},{"code":"0506","name":"药枕"},{"code":"0507","name":"出牙剂"}],"imgAddr":"39e68345/cac8a579/77c3b5ee/1b801cea/logo_middle.jpg","internationalClasses":5,"localImageAddr":"quandashi/2018/6/15/85f218d98eaaccac03e8a6bfad775b7a.jpg","mark":"老亲妈","publishedOppositionDate":1502553600000,"registrationDate":1510502400000,"serialNumber":"21341674","showPossessionTermStart":"暂无","showPublishedOppositionDate":"2017-08-13","showRegistrationDate":"2017-11-13"},{"applicantName":"符德广","correspondent":"山东欧赛网络科技有限公司","flowLists":[],"goodsLists":[{"code":"3012","name":"食用淀粉"},{"code":"3008","name":"米粉（粉状）"},{"code":"3009","name":"方便粉丝"},{"code":"3006","name":"糕点"},{"code":"3006","name":"甜食"},{"code":"3004","name":"甜食"},{"code":"3009","name":"米粉（条状）"},{"code":"3008","name":"谷粉"},{"code":"3002","name":"茶饮料"},{"code":"3018","name":"食品用香料（含醚香料和香精油除外）"},{"code":"3016","name":"调味品"}],"imgAddr":"6b5a560a/e597eb29/1f1f1271/aae3661a/logo_middle.jpg","internationalClasses":30,"localImageAddr":"quandashi/2018/6/15/e906d7d523b3a05a3cc1eb644b067345.jpg","mark":"老谭妈","publishedOppositionDate":1518451200000,"registrationDate":1526140800000,"serialNumber":"22904023","showPossessionTermStart":"暂无","showPublishedOppositionDate":"2018-02-13","showRegistrationDate":"2018-05-13"},{"applicantName":"刘志国","correspondent":"北京聚集科技有限公司","flowLists":[{"name":"等待驳回通知发文","showLastTime":"2017-03-27"},{"name":"等待受理通知书发文","showLastTime":"2016-10-19"},{"name":"申请收文","showLastTime":"2016-05-17"}],"goodsLists":[{"code":"3501","name":"广告宣传"},{"code":"3501","name":"商业橱窗布置"},{"code":"3501","name":"计算机网络上的在线广告"},{"code":"3502","name":"特许经营的商业管理"},{"code":"3502","name":"饭店商业管理"},{"code":"3502","name":"通过网站提供商业信息"},{"code":"3503","name":"市场营销"},{"code":"3503","name":"为商品和服务的买卖双方提供在线市场"},{"code":"3503","name":"替他人推销"},{"code":"3506","name":"开发票"}],"imgAddr":"217fc85e/6ec1fa6e/e0053ca0/1a57e547/logo_middle.jpg","internationalClasses":35,"localImageAddr":"quandashi/2018/6/15/b6d1e04580ef8fcf4b56abecb6d060dc.jpg","mark":"老祥妈","possessionTermStart":1497369600000,"registrationDate":1497369600000,"serialNumber":"19769741","showPossessionTermStart":"2017-06-14","showPublishedOppositionDate":"暂无","showRegistrationDate":"2017-06-14"},{"applicantName":"冷文革","correspondent":"南昌卓尔商标事务所有限公司","flowLists":[{"name":"等待注册证发文","showLastTime":"2017-01-07"},{"name":"商标注册申请完成","showLastTime":"2017-01-07"},{"name":"商标注册申请注册公告排版完成","showLastTime":"2016-10-29"},{"name":"等待受理通知书发文","showLastTime":"2015-12-28"},{"name":"申请收文","showLastTime":"2015-09-18"}],"goodsLists":[{"code":"2904","name":"以果蔬为主的零食小吃"},{"code":"2905","name":"干蔬菜"},{"code":"2905","name":"榨菜"},{"code":"2905","name":"笋干"},{"code":"2905","name":"腐乳"},{"code":"2905","name":"腌制蔬菜"},{"code":"2905","name":"萝卜干"},{"code":"2911","name":"以果蔬为主的零食小吃"},{"code":"2912","name":"干食用菌"},{"code":"2913","name":"腐竹"},{"code":"2913","name":"豆腐"}],"imgAddr":"1a6a00db/cbd4c982/1d3b535a/2a1799c2/logo_middle.jpg","internationalClasses":29,"localImageAddr":"quandashi/2018/6/15/56c1ed2c8c1e6dff0751edc8f2bc2f18.jpg","mark":"老丁妈","possessionTermStart":1477584000000,"publishedOppositionDate":1469548800000,"registrationDate":1477584000000,"serialNumber":"17935356","showPossessionTermStart":"2016-10-28","showPublishedOppositionDate":"2016-07-27","showRegistrationDate":"2016-10-28"},{"applicantName":"白光龙","correspondent":"贵州华信商标代理有限公司","flowLists":[{"name":"商标已注册","showLastTime":"2007-09-03"},{"name":"注册申请初步审定","showLastTime":"2007-03-23"},{"name":"商标注册申请中","showLastTime":"2005-01-19"}],"goodsLists":[{"code":"3016","name":"调味品"},{"code":"3016","name":"调味品(辣)"},{"code":"3016","name":"辣椒粉"},{"code":"3016","name":"番茄酱(调味品)"},{"code":"3016","name":"调味酱"},{"code":"3016","name":"酱菜(调味品)"},{"code":"3016","name":"豆豉"},{"code":"3016","name":"辣椒油"},{"code":"3016","name":"花椒粉"},{"code":"3016","name":"胡椒"}],"imgAddr":"dc7058de/f1317a18/f3668cbd/2c46c0fd/logo_middle.jpg","internationalClasses":30,"localImageAddr":"quandashi/2018/6/15/d216719975bff6f91f806673ea2c1802.jpg","mark":"老白妈","possessionTermStart":1187020800000,"publishedOppositionDate":1179072000000,"registrationDate":1187020800000,"serialNumber":"4470416","showPossessionTermStart":"2007-08-14","showPublishedOppositionDate":"2007-05-14","showRegistrationDate":"2007-08-14"},{"applicantName":"欧阳晃生","flowLists":[{"name":"等待受理通知书发文"}],"goodsLists":[{"code":"3016","name":"肉桂粉（调味品）"},{"code":"3019","name":"家用嫩肉剂"},{"code":"3016","name":"调味酱汁"},{"code":"3016","name":"调味品"},{"code":"3016","name":"调味肉汁"},{"code":"3008","name":"谷类制品"},{"code":"3007","name":"盒饭"},{"code":"3004","name":"糖"},{"code":"3003","name":"糖"},{"code":"3016","name":"调味料"},{"code":"3017","name":"烹饪用碱"}],"imgAddr":"14d5aa30/eed45280/42481323/a266629d/logo_middle.jpg","internationalClasses":30,"localImageAddr":"quandashi/2018/6/15/941640572977b32561eceb524f0f97fb.jpg","mark":"老卤妈","publishedOppositionDate":1525536000000,"serialNumber":"25459504","showPossessionTermStart":"暂无","showPublishedOppositionDate":"2018-05-06","showRegistrationDate":"暂无"},{"applicantName":"王慧婵","correspondent":"中国商标专利事务所有限公司","flowLists":[],"goodsLists":[{"code":"3009","name":"方便面"},{"code":"3008","name":"米"},{"code":"3009","name":"面条"},{"code":"3016","name":"番茄酱（调味品）"},{"code":"3002","name":"茶"},{"code":"","name":"米粉"},{"code":"3012","name":"地瓜粉"},{"code":"3006","name":"饼干"},{"code":"3006","name":"燕麦食品"},{"code":"3006","name":"面包"},{"code":"3009","name":"通心粉"},{"code":"3008","name":"面粉"},{"code":"3012","name":"粉丝（条）"},{"code":"3006","name":"月饼"}],"imgAddr":"0a0e626c/eb3fc73b/b9cee948/510952c4/logo_middle.jpg","internationalClasses":30,"localImageAddr":"quandashi/2018/6/15/944259da69b39e7dc8c8ca9054a0c553.jpg","mark":"老莞妈","publishedOppositionDate":1510502400000,"registrationDate":1518451200000,"serialNumber":"22493486","showPossessionTermStart":"暂无","showPublishedOppositionDate":"2017-11-13","showRegistrationDate":"2018-02-13"},{"applicantName":"童小军","correspondent":"北京标邦知识产权代理有限公司","flowLists":[{"name":"商标无效"},{"name":"商标注册申请等待驳回复审","showLastTime":"2015-01-27"},{"name":"商标注册申请驳回通知发文","showLastTime":"2014-12-02"},{"name":"商标注册申请中","showLastTime":"2013-11-12"}],"goodsLists":[{"code":"2906","name":"蛋"},{"code":"2907","name":"奶油(奶制品)"},{"code":"2907","name":"豆奶(牛奶替代品)"},{"code":"2911","name":"加工过的种子"},{"code":"2912","name":"木耳"},{"code":"2913","name":"烹饪用蛋白"},{"code":"2913","name":"腐竹"},{"code":"2912","name":"干食用菌"},{"code":"2913","name":"豆腐制品"},{"code":"2913","name":"豆腐"}],"imgAddr":"3cfab0d1/f1135e27/0a1865b0/3c4d9d8e/logo_middle.jpg","internationalClasses":29,"localImageAddr":"quandashi/2018/6/15/cfdf0c6fb3763f708e2c8228c2b85820.jpg","mark":"老佛妈","serialNumber":"13525411","showPossessionTermStart":"暂无","showPublishedOppositionDate":"暂无","showRegistrationDate":"暂无"}]